redocmx/__init__.py
redocmx/addenda.py
redocmx/cfdi.py
redocmx/file.py
redocmx/pdf.py
redocmx/redoc.py
redocmx/service.py
redocmx-0.0.2.dist-info/LICENSE
redocmx-0.0.2.dist-info/METADATA
redocmx-0.0.2.dist-info/WHEEL
redocmx-0.0.2.dist-info/top_level.txt
redocmx-0.0.2.dist-info/RECORD
