Metadata-Version: 2.1
Name: redocmx
Version: 0.0.2
Summary: Conversión CFDI a PDF
Home-page: https://github.com/redocmx/client-python
Author: redoc.mx
Author-email: soporte@redoc.mx
License: MIT
Keywords: cfdi a pdf,cfdi,cfdi to pdf,conversión cfdi a pdf,sat mexico,mexico
Classifier: Programming Language :: Python :: 3
Classifier: License :: OSI Approved :: MIT License
Classifier: Operating System :: OS Independent
Requires-Python: >=3.6
License-File: LICENSE
Requires-Dist: requests
